django_custom_utils/__init__.py
django_custom_utils/admin.py
django_custom_utils/fields.py
django_custom_utils/filters.py
django_custom_utils/managers.py
django_custom_utils/models.py
django_custom_utils/utils.py
django_custom_utils/views.py
django_custom_utils-0.1.1.dist-info/LICENSE
django_custom_utils-0.1.1.dist-info/METADATA
django_custom_utils-0.1.1.dist-info/WHEEL
django_custom_utils-0.1.1.dist-info/RECORD
